wiresense/__init__.py
wiresense/wiresense.py
wiresense-1.0.2.dist-info/METADATA
wiresense-1.0.2.dist-info/WHEEL
wiresense-1.0.2.dist-info/licenses/LICENSE
wiresense-1.0.2.dist-info/RECORD
