Metadata-Version: 2.3
Name: wiresense
Version: 1.0.2
Summary: Client library for Wiresense
Project-URL: Homepage, https://github.com/Wiresense/wiresense.py#readme
Project-URL: Issues, https://github.com/Wiresense/wiresense.py/issues
Author: Saladrian
License-File: LICENSE
Classifier: License :: OSI Approved :: MIT License
Classifier: Operating System :: OS Independent
Classifier: Programming Language :: Python :: 3
Requires-Python: >=3.8
Requires-Dist: aiohttp>=3.9.5
Requires-Dist: websockets>=12.0
